comicapi/__init__.py
comicapi/comet.py
comicapi/comicarchive.py
comicapi/comicbookinfo.py
comicapi/comicinfoxml.py
comicapi/filenamelexer.py
comicapi/filenameparser.py
comicapi/genericmetadata.py
comicapi/issuestring.py
comicapi/utils.py
comicapi/__pyinstaller/__init__.py
comicapi/__pyinstaller/hook-comicapi.py
comicapi/__pyinstaller/hook-wordninja.py
comicapi/archivers/__init__.py
comicapi/archivers/archiver.py
comicapi/archivers/folder.py
comicapi/archivers/rar.py
comicapi/archivers/sevenzip.py
comicapi/archivers/tar.py
comicapi/archivers/zip.py
comicapi/data/__init__.py
comicapi/data/publishers.json
comicapi-3.2.0.dist-info/LICENSE
comicapi-3.2.0.dist-info/METADATA
comicapi-3.2.0.dist-info/WHEEL
comicapi-3.2.0.dist-info/entry_points.txt
comicapi-3.2.0.dist-info/top_level.txt
comicapi-3.2.0.dist-info/RECORD
